Workbook
Name anos: 'INVEST PLANNER'!$D$9
Name aporte: 'INVEST PLANNER'!$D$8
Name investimento: 'INVEST PLANNER'!$D$8
Name investimento_mensal: 'INVEST PLANNER'!$D$8
Name patrimonio: 'INVEST PLANNER'!$D$11
Name qtd_anos: 'INVEST PLANNER'!$D$9
Name rendimento_carteira: 'INVEST PLANNER'!$D$4
Name salario: 'INVEST PLANNER'!$D$3
Name sugestao_investimento: 'INVEST PLANNER'!$D$5
Name taxa_mensal: 'INVEST PLANNER'!$D$10

Sheet INVEST PLANNER
B2: CONFIGURAÇÕES
B3: Salário | D3: 4000
B4: Rendimento médio mensal carteira | D4: 0.006
B5: Sugestão de investimento (30% salário) | D5: =D3*30% -> 1200
B7: INVESTIMENTO MENSAL
B8: Valor investido por mês | D8: =sugestao_investimento -> 1200
B9: Por quantos anos | D9: 10
B10: Taxa de rendimento média mensal | D10: 0.01079
B11: Patrimônio acumulado | D11: =FV(taxa_mensal,qtd_anos*12,-ABS(aporte)) -> 291941.06
B12: Dividendos mensais | D12: =patrimonio*rendimento_carteira -> 1751.6463
B14: CENÁRIOS | C14: PATRIMÔNIO | D14: DIVIDENDOS
A15: 2 | B15: Quanto em 2 anos? | C15: =FV($D$10,$A15*12,-ABS($D$8)) -> 32673.153 | D15: =C15*rendimento_carteira -> 196.03892
A16: 5 | B16: Quanto em 5 anos? | C16: =FV($D$10,$A16*12,-ABS($D$8)) -> 100532.3 | D16: =C16*rendimento_carteira -> 603.19378
A17: 10 | B17: Quanto em 10 anos? | C17: =FV($D$10,$A17*12,-ABS($D$8)) -> 291941.06 | D17: =C17*rendimento_carteira -> 1751.6463
A18: 20 | B18: Quanto em 20 anos? | C18: =FV($D$10,$A18*12,-ABS($D$8)) -> 1350238.1 | D18: =C18*rendimento_carteira -> 8101.4285
A19: 30 | B19: Quanto em 30 anos? | C19: =FV($D$10,$A19*12,-ABS($D$8)) -> 5186603.6 | D19: =C19*rendimento_carteira -> 31119.622
B21: DISTRIBUIÇÃO DO INVESTIMENTO SUGERIDA
B23: Selecione o perfil | C23: Agressivo
B25: Investimento mensal | C25: =aporte -> 1200
B27: TIPO DE FII | C27: Percentual Sugerido | D27: Valor do Investimento
B28: PAPEL | C28: =VLOOKUP($C$23&"-"&B28,'Investimento por perfil e tipo'!$A:$D,4,0) -> 0.5 | D28: =C28*$C$25 -> 600
B29: TIJOLO | C29: =VLOOKUP($C$23&"-"&B29,'Investimento por perfil e tipo'!$A:$D,4,0) -> 0.1 | D29: =C29*$C$25 -> 120
B30: HÍBRIDOS | C30: =VLOOKUP($C$23&"-"&B30,'Investimento por perfil e tipo'!$A:$D,4,0) -> 0.05 | D30: =C30*$C$25 -> 60
B31: FOFs | C31: =VLOOKUP($C$23&"-"&B31,'Investimento por perfil e tipo'!$A:$D,4,0) -> 0.05 | D31: =C31*$C$25 -> 60
B32: DESENVOLVIMENTO | C32: =VLOOKUP($C$23&"-"&B32,'Investimento por perfil e tipo'!$A:$D,4,0) -> 0.2 | D32: =C32*$C$25 -> 240
B33: HOTELARIAS | C33: =VLOOKUP($C$23&"-"&B33,'Investimento por perfil e tipo'!$A:$D,4,0) -> 0.1 | D33: =C33*$C$25 -> 120
D34: =SUM(D28:D33) -> 1200

Sheet Investimento por perfil e tipo
A2: CHAVE | B2: PERFIL | C2: TIPO DE FII | D2: %
A3: =B3&"-"&C3 -> Conservador-PAPEL | B3: Conservador | C3: PAPEL | D3: 0.3
A4: =B4&"-"&C4 -> Conservador-TIJOLO | B4: Conservador | C4: TIJOLO | D4: 0.5
A5: =B5&"-"&C5 -> Conservador-HÍBRIDOS | B5: Conservador | C5: HÍBRIDOS | D5: 0.1
A6: =B6&"-"&C6 -> Conservador-FOFs | B6: Conservador | C6: FOFs | D6: 0.1
A7: =B7&"-"&C7 -> Conservador-DESENVOLVIMENTO | B7: Conservador | C7: DESENVOLVIMENTO | D7: 0
A8: =B8&"-"&C8 -> Conservador-HOTELARIAS | B8: Conservador | C8: HOTELARIAS | D8: 0
A9: =B9&"-"&C9 -> Moderado-PAPEL | B9: Moderado | C9: PAPEL | D9: 0.32
A10: =B10&"-"&C10 -> Moderado-TIJOLO | B10: Moderado | C10: TIJOLO | D10: 0.35
A11: =B11&"-"&C11 -> Moderado-HÍBRIDOS | B11: Moderado | C11: HÍBRIDOS | D11: 0.08
A12: =B12&"-"&C12 -> Moderado-FOFs | B12: Moderado | C12: FOFs | D12: 0.05
A13: =B13&"-"&C13 -> Moderado-DESENVOLVIMENTO | B13: Moderado | C13: DESENVOLVIMENTO | D13: 0.1
A14: =B14&"-"&C14 -> Moderado-HOTELARIAS | B14: Moderado | C14: HOTELARIAS | D14: 0.1
... A20: =B20&"-"&C20 -> Agressivo-HOTELARIAS | B20: Agressivo | C20: HOTELARIAS | D20: 0.1
